{
"instructions_readme": "1) Open Chrome, 2) go to chrome://tracing, 3) click Load, 4) navigate to this file.",

"traceEvents":[
{ "pid": 1, "tid": 1, "ph": "M", "name": "thread_name", "args": { "name": "" } },
{ "pid": 1, "tid": 1, "ts": 1.00000004749745, "dur": 14898758.7890625, "ph": "X", "name": "il2cpp.exe", "args": { "durationMS": 14898.7587890625, "detail": "" } },
{ "pid": 1, "tid": 1, "ts": 202987.014770508, "dur": 14692885.7421875, "ph": "X", "name": "ConvertAssemblies", "args": { "durationMS": 14692.8857421875, "detail": "" } },
{ "pid": 1, "tid": 1, "ts": 228643.005371094, "dur": 90470.0012207031, "ph": "X", "name": "Collect assemblies to convert", "args": { "durationMS": 90.4700012207031, "detail": "" } },
{ "pid": 1, "tid": 1, "ts": 319257.965087891, "dur": 82077.995300293, "ph": "X", "name": "RegisterCorlib", "args": { "durationMS": 82.077995300293, "detail": "" } },
{ "pid": 1, "tid": 1, "ts": 401635.986328125, "dur": 65939.0029907227, "ph": "X", "name": "PreProcessIL", "args": { "durationMS": 65.9390029907227, "detail": "" } },
{ "pid": 1, "tid": 1, "ts": 401635.986328125, "dur": 18523.0007171631, "ph": "X", "name": "Inject base types and finalizers into COM and Windows Runtime types", "args": { "durationMS": 18.5230007171631, "detail": "" } },
{ "pid": 1, "tid": 1, "ts": 402016.998291016, "dur": 12856.0009002686, "ph": "X", "name": "ModifyCOMAndWindowsRuntimeTypes in assembly", "args": { "durationMS": 12.8560009002686, "detail": "mscorlib" } },
{ "pid": 1, "tid": 1, "ts": 414873.962402344, "dur": 2112.99991607666, "ph": "X", "name": "ModifyCOMAndWindowsRuntimeTypes in assembly", "args": { "durationMS": 2.11299991607666, "detail": "Mono.Security" } },
{ "pid": 1, "tid": 1, "ts": 417542.999267578, "dur": 1044.0000295639, "ph": "X", "name": "ModifyCOMAndWindowsRuntimeTypes in assembly", "args": { "durationMS": 1.0440000295639, "detail": "UnityEngine.CoreModule" } },
{ "pid": 1, "tid": 1, "ts": 418953.002929688, "dur": 787.000000476837, "ph": "X", "name": "ModifyCOMAndWindowsRuntimeTypes in assembly", "args": { "durationMS": 0.787000000476837, "detail": "UnityEngine.UI" } },
{ "pid": 1, "tid": 1, "ts": 419740.997314453, "dur": 395.000010728836, "ph": "X", "name": "ModifyCOMAndWindowsRuntimeTypes in assembly", "args": { "durationMS": 0.395000010728836, "detail": "Vuforia.UnityExtensions" } },
{ "pid": 1, "tid": 1, "ts": 420158.996582031, "dur": 47415.0009155273, "ph": "X", "name": "ApplyDefaultMarshalAsAttribute", "args": { "durationMS": 47.4150009155273, "detail": "" } },
{ "pid": 1, "tid": 1, "ts": 420494.995117188, "dur": 28466.9990539551, "ph": "X", "name": "ApplyDefaultMarshalAsAttributeVisitor in assembly", "args": { "durationMS": 28.4669990539551, "detail": "mscorlib" } },
{ "pid": 1, "tid": 1, "ts": 448993.011474609, "dur": 10789.999961853, "ph": "X", "name": "ApplyDefaultMarshalAsAttributeVisitor in assembly", "args": { "durationMS": 10.789999961853, "detail": "System" } },
{ "pid": 1, "tid": 1, "ts": 460120.971679688, "dur": 1720.99995613098, "ph": "X", "name": "ApplyDefaultMarshalAsAttributeVisitor in assembly", "args": { "durationMS": 1.72099995613098, "detail": "UnityEngine.CoreModule" } },
{ "pid": 1, "tid": 1, "ts": 462846.008300781, "dur": 1475.99995136261, "ph": "X", "name": "ApplyDefaultMarshalAsAttributeVisitor in assembly", "args": { "durationMS": 1.47599995136261, "detail": "UnityEngine.UI" } },
{ "pid": 1, "tid": 1, "ts": 464323.028564453, "dur": 3190.00005722046, "ph": "X", "name": "ApplyDefaultMarshalAsAttributeVisitor in assembly", "args": { "durationMS": 3.19000005722046, "detail": "Vuforia.UnityExtensions" } },
{ "pid": 1, "tid": 1, "ts": 467796.997070312, "dur": 7094.00033950806, "ph": "X", "name": "WriteResources", "args": { "durationMS": 7.09400033950806, "detail": "" } },
{ "pid": 1, "tid": 1, "ts": 475174.011230469, "dur": 62728.0006408691, "ph": "X", "name": "CopyEtcFolder", "args": { "durationMS": 62.7280006408691, "detail": "" } },
{ "pid": 1, "tid": 1, "ts": 538437.98828125, "dur": 308160.980224609, "ph": "X", "name": "PreProcessStage", "args": { "durationMS": 308.160980224609, "detail": "" } },
{ "pid": 1, "tid": 1, "ts": 846604.98046875, "dur": 2227.9999256134, "ph": "X", "name": "Debugger Sequence Points", "args": { "durationMS": 2.2279999256134, "detail": "" } },
{ "pid": 1, "tid": 1, "ts": 849513.000488281, "dur": 1817677.00195312, "ph": "X", "name": "Generics Collection", "args": { "durationMS": 1817.67700195312, "detail": "" } },
{ "pid": 1, "tid": 1, "ts": 849513.000488281, "dur": 1773138.06152344, "ph": "X", "name": "GenericsCollector.Collect", "args": { "durationMS": 1773.13806152344, "detail": "" } },
{ "pid": 1, "tid": 1, "ts": 2622650.87890625, "dur": 40680.0003051758, "ph": "X", "name": "CollectGenericVirtualMethods.Collect", "args": { "durationMS": 40.6800003051758, "detail": "" } },
{ "pid": 1, "tid": 1, "ts": 2663332.27539062, "dur": 3282.99999237061, "ph": "X", "name": "AddExtraTypes", "args": { "durationMS": 3.28299999237061, "detail": "" } },
{ "pid": 1, "tid": 1, "ts": 2667190.91796875, "dur": 2529.99997138977, "ph": "X", "name": "Add Windows Runtime type names", "args": { "durationMS": 2.52999997138977, "detail": "" } },
{ "pid": 1, "tid": 1, "ts": 2667190.91796875, "dur": 2529.99997138977, "ph": "X", "name": "Add Windows Runtime type names", "args": { "durationMS": 2.52999997138977, "detail": "" } },
{ "pid": 1, "tid": 1, "ts": 2702818.11523438, "dur": 5941125, "ph": "X", "name": "AllAssemblyConversion", "args": { "durationMS": 5941.125, "detail": "" } },
{ "pid": 1, "tid": 1, "ts": 2713871.09375, "dur": 3057047.11914062, "ph": "X", "name": "Convert", "args": { "durationMS": 3057.04711914062, "detail": "mscorlib" } },
{ "pid": 1, "tid": 1, "ts": 2713873.046875, "dur": 3057043.9453125, "ph": "X", "name": "Code", "args": { "durationMS": 3057.0439453125, "detail": "" } },
{ "pid": 1, "tid": 1, "ts": 2714546.875, "dur": 3056368.89648438, "ph": "X", "name": "Methods", "args": { "durationMS": 3056.36889648438, "detail": "Definitions" } },
{ "pid": 1, "tid": 1, "ts": 5775812.98828125, "dur": 8020.99990844727, "ph": "X", "name": "Convert", "args": { "durationMS": 8.02099990844727, "detail": "Mono.Security" } },
{ "pid": 1, "tid": 1, "ts": 5775814.94140625, "dur": 8019.00005340576, "ph": "X", "name": "Code", "args": { "durationMS": 8.01900005340576, "detail": "" } },
{ "pid": 1, "tid": 1, "ts": 5775831.0546875, "dur": 8001.9998550415, "ph": "X", "name": "Methods", "args": { "durationMS": 8.0019998550415, "detail": "Definitions" } },
{ "pid": 1, "tid": 1, "ts": 5788300.78125, "dur": 332740.997314453, "ph": "X", "name": "Convert", "args": { "durationMS": 332.740997314453, "detail": "System" } },
{ "pid": 1, "tid": 1, "ts": 5788302.24609375, "dur": 332739.990234375, "ph": "X", "name": "Code", "args": { "durationMS": 332.739990234375, "detail": "" } },
{ "pid": 1, "tid": 1, "ts": 5788346.19140625, "dur": 332695.983886719, "ph": "X", "name": "Methods", "args": { "durationMS": 332.695983886719, "detail": "Definitions" } },
{ "pid": 1, "tid": 1, "ts": 6125630.859375, "dur": 3572.00002670288, "ph": "X", "name": "Convert", "args": { "durationMS": 3.57200002670288, "detail": "System.Configuration" } },
{ "pid": 1, "tid": 1, "ts": 6125633.30078125, "dur": 3569.00000572205, "ph": "X", "name": "Code", "args": { "durationMS": 3.56900000572205, "detail": "" } },
{ "pid": 1, "tid": 1, "ts": 6125646.97265625, "dur": 3555.0000667572, "ph": "X", "name": "Methods", "args": { "durationMS": 3.5550000667572, "detail": "Definitions" } },
{ "pid": 1, "tid": 1, "ts": 6133294.921875, "dur": 634.999990463257, "ph": "X", "name": "Convert", "args": { "durationMS": 0.634999990463257, "detail": "System.Xml" } },
{ "pid": 1, "tid": 1, "ts": 6133297.36328125, "dur": 633.000016212463, "ph": "X", "name": "Code", "args": { "durationMS": 0.633000016212463, "detail": "" } },
{ "pid": 1, "tid": 1, "ts": 6133305.17578125, "dur": 625, "ph": "X", "name": "Methods", "args": { "durationMS": 0.625, "detail": "Definitions" } },
{ "pid": 1, "tid": 1, "ts": 6138304.19921875, "dur": 1194.00000572205, "ph": "X", "name": "Convert", "args": { "durationMS": 1.19400000572205, "detail": "System.Core" } },
{ "pid": 1, "tid": 1, "ts": 6138306.15234375, "dur": 1192.00003147125, "ph": "X", "name": "Code", "args": { "durationMS": 1.19200003147125, "detail": "" } },
{ "pid": 1, "tid": 1, "ts": 6138318.84765625, "dur": 1179.00002002716, "ph": "X", "name": "Methods", "args": { "durationMS": 1.17900002002716, "detail": "Definitions" } },
{ "pid": 1, "tid": 1, "ts": 6145562.01171875, "dur": 11121.9997406006, "ph": "X", "name": "Convert", "args": { "durationMS": 11.1219997406006, "detail": "UnityEngine.SharedInternalsModule" } },
{ "pid": 1, "tid": 1, "ts": 6145563.96484375, "dur": 11119.9998855591, "ph": "X", "name": "Code", "args": { "durationMS": 11.1199998855591, "detail": "" } },
{ "pid": 1, "tid": 1, "ts": 6145579.1015625, "dur": 11105.0004959106, "ph": "X", "name": "Methods", "args": { "durationMS": 11.1050004959106, "detail": "Definitions" } },
{ "pid": 1, "tid": 1, "ts": 6161653.3203125, "dur": 342479.00390625, "ph": "X", "name": "Convert", "args": { "durationMS": 342.47900390625, "detail": "UnityEngine.CoreModule" } },
{ "pid": 1, "tid": 1, "ts": 6161654.78515625, "dur": 342476.989746094, "ph": "X", "name": "Code", "args": { "durationMS": 342.476989746094, "detail": "" } },
{ "pid": 1, "tid": 1, "ts": 6161787.109375, "dur": 342343.994140625, "ph": "X", "name": "Methods", "args": { "durationMS": 342.343994140625, "detail": "Definitions" } },
{ "pid": 1, "tid": 1, "ts": 6509246.58203125, "dur": 10046.9999313354, "ph": "X", "name": "Convert", "args": { "durationMS": 10.0469999313354, "detail": "UnityEngine.AudioModule" } },
{ "pid": 1, "tid": 1, "ts": 6509248.046875, "dur": 10046.0004806519, "ph": "X", "name": "Code", "args": { "durationMS": 10.0460004806519, "detail": "" } },
{ "pid": 1, "tid": 1, "ts": 6509262.20703125, "dur": 10031.9995880127, "ph": "X", "name": "Methods", "args": { "durationMS": 10.0319995880127, "detail": "Definitions" } },
{ "pid": 1, "tid": 1, "ts": 6523957.51953125, "dur": 27729.0000915527, "ph": "X", "name": "Convert", "args": { "durationMS": 27.7290000915527, "detail": "UnityEngine.TextRenderingModule" } },
{ "pid": 1, "tid": 1, "ts": 6523958.984375, "dur": 27726.9992828369, "ph": "X", "name": "Code", "args": { "durationMS": 27.7269992828369, "detail": "" } },
{ "pid": 1, "tid": 1, "ts": 6523968.75, "dur": 27715.9996032715, "ph": "X", "name": "Methods", "args": { "durationMS": 27.7159996032715, "detail": "Definitions" } },
{ "pid": 1, "tid": 1, "ts": 6557619.140625, "dur": 972.000002861023, "ph": "X", "name": "Convert", "args": { "durationMS": 0.972000002861023, "detail": "System.Diagnostics.StackTrace" } },
{ "pid": 1, "tid": 1, "ts": 6557620.1171875, "dur": 970.000028610229, "ph": "X", "name": "Code", "args": { "durationMS": 0.970000028610229, "detail": "" } },
{ "pid": 1, "tid": 1, "ts": 6557627.9296875, "dur": 962.000012397766, "ph": "X", "name": "Methods", "args": { "durationMS": 0.962000012397766, "detail": "Definitions" } },
{ "pid": 1, "tid": 1, "ts": 6577482.421875, "dur": 526.000022888184, "ph": "X", "name": "Convert", "args": { "durationMS": 0.526000022888184, "detail": "System.Globalization.Extensions" } },
{ "pid": 1, "tid": 1, "ts": 6577482.91015625, "dur": 524.999976158142, "ph": "X", "name": "Code", "args": { "durationMS": 0.524999976158142, "detail": "" } },
{ "pid": 1, "tid": 1, "ts": 6577490.72265625, "dur": 515.999972820282, "ph": "X", "name": "Methods", "args": { "durationMS": 0.515999972820282, "detail": "Definitions" } },
{ "pid": 1, "tid": 1, "ts": 6582255.859375, "dur": 16752.0008087158, "ph": "X", "name": "Convert", "args": { "durationMS": 16.7520008087158, "detail": "UnityEngine.AnimationModule" } },
{ "pid": 1, "tid": 1, "ts": 6582258.30078125, "dur": 16750, "ph": "X", "name": "Code", "args": { "durationMS": 16.75, "detail": "" } },
{ "pid": 1, "tid": 1, "ts": 6582273.92578125, "dur": 16733.9992523193, "ph": "X", "name": "Methods", "args": { "durationMS": 16.7339992523193, "detail": "Definitions" } },
{ "pid": 1, "tid": 1, "ts": 6603604.00390625, "dur": 29110.9981536865, "ph": "X", "name": "Convert", "args": { "durationMS": 29.1109981536865, "detail": "UnityEngine.GameCenterModule" } },
{ "pid": 1, "tid": 1, "ts": 6603605.95703125, "dur": 29108.0017089844, "ph": "X", "name": "Code", "args": { "durationMS": 29.1080017089844, "detail": "" } },
{ "pid": 1, "tid": 1, "ts": 6603625, "dur": 29088.9987945557, "ph": "X", "name": "Methods", "args": { "durationMS": 29.0889987945557, "detail": "Definitions" } },
{ "pid": 1, "tid": 1, "ts": 6637161.1328125, "dur": 91779.9987792969, "ph": "X", "name": "Convert", "args": { "durationMS": 91.7799987792969, "detail": "UnityEngine.IMGUIModule" } },
{ "pid": 1, "tid": 1, "ts": 6637163.0859375, "dur": 91777.0004272461, "ph": "X", "name": "Code", "args": { "durationMS": 91.7770004272461, "detail": "" } },
{ "pid": 1, "tid": 1, "ts": 6637181.15234375, "dur": 91759.0026855469, "ph": "X", "name": "Methods", "args": { "durationMS": 91.7590026855469, "detail": "Definitions" } },
{ "pid": 1, "tid": 1, "ts": 6733345.703125, "dur": 925.999999046326, "ph": "X", "name": "Convert", "args": { "durationMS": 0.925999999046326, "detail": "UnityEngine.ImageConversionModule" } },
{ "pid": 1, "tid": 1, "ts": 6733348.14453125, "dur": 924.000024795532, "ph": "X", "name": "Code", "args": { "durationMS": 0.924000024795532, "detail": "" } },
{ "pid": 1, "tid": 1, "ts": 6733355.95703125, "dur": 915.000021457672, "ph": "X", "name": "Methods", "args": { "durationMS": 0.915000021457672, "detail": "Definitions" } },
{ "pid": 1, "tid": 1, "ts": 6738837.40234375, "dur": 11182.9996109009, "ph": "X", "name": "Convert", "args": { "durationMS": 11.1829996109009, "detail": "UnityEngine.InputLegacyModule" } },
{ "pid": 1, "tid": 1, "ts": 6738837.890625, "dur": 11182.0001602173, "ph": "X", "name": "Code", "args": { "durationMS": 11.1820001602173, "detail": "" } },
{ "pid": 1, "tid": 1, "ts": 6738847.16796875, "dur": 11171.9999313354, "ph": "X", "name": "Methods", "args": { "durationMS": 11.1719999313354, "detail": "Definitions" } },
{ "pid": 1, "tid": 1, "ts": 6754165.52734375, "dur": 2558.00008773804, "ph": "X", "name": "Convert", "args": { "durationMS": 2.55800008773804, "detail": "UnityEngine.Physics2DModule" } },
{ "pid": 1, "tid": 1, "ts": 6754166.015625, "dur": 2556.99992179871, "ph": "X", "name": "Code", "args": { "durationMS": 2.55699992179871, "detail": "" } },
{ "pid": 1, "tid": 1, "ts": 6754175.78125, "dur": 2547.00016975403, "ph": "X", "name": "Methods", "args": { "durationMS": 2.54700016975403, "detail": "Definitions" } },
{ "pid": 1, "tid": 1, "ts": 6761500, "dur": 13265.9997940063, "ph": "X", "name": "Convert", "args": { "durationMS": 13.2659997940063, "detail": "UnityEngine.PhysicsModule" } },
{ "pid": 1, "tid": 1, "ts": 6761502.44140625, "dur": 13263.9999389648, "ph": "X", "name": "Code", "args": { "durationMS": 13.2639999389648, "detail": "" } },
{ "pid": 1, "tid": 1, "ts": 6761513.671875, "dur": 13251.0004043579, "ph": "X", "name": "Methods", "args": { "durationMS": 13.2510004043579, "detail": "Definitions" } },
{ "pid": 1, "tid": 1, "ts": 6779730.95703125, "dur": 11484.0002059937, "ph": "X", "name": "Convert", "args": { "durationMS": 11.4840002059937, "detail": "UnityEngine.UIModule" } },
{ "pid": 1, "tid": 1, "ts": 6779732.91015625, "dur": 11482.0003509521, "ph": "X", "name": "Code", "args": { "durationMS": 11.4820003509521, "detail": "" } },
{ "pid": 1, "tid": 1, "ts": 6779746.09375, "dur": 11468.0004119873, "ph": "X", "name": "Methods", "args": { "durationMS": 11.4680004119873, "detail": "Definitions" } },
{ "pid": 1, "tid": 1, "ts": 6796174.8046875, "dur": 3795.00007629395, "ph": "X", "name": "Convert", "args": { "durationMS": 3.79500007629395, "detail": "UnityEngine.UnityAnalyticsModule" } },
{ "pid": 1, "tid": 1, "ts": 6796175.78125, "dur": 3792.99998283386, "ph": "X", "name": "Code", "args": { "durationMS": 3.79299998283386, "detail": "" } },
{ "pid": 1, "tid": 1, "ts": 6796187.01171875, "dur": 3782.00006484985, "ph": "X", "name": "Methods", "args": { "durationMS": 3.78200006484985, "detail": "Definitions" } },
{ "pid": 1, "tid": 1, "ts": 6804707.51953125, "dur": 2464.99991416931, "ph": "X", "name": "Convert", "args": { "durationMS": 2.46499991416931, "detail": "UnityEngine.UnityWebRequestModule" } },
{ "pid": 1, "tid": 1, "ts": 6804708.984375, "dur": 2463.00005912781, "ph": "X", "name": "Code", "args": { "durationMS": 2.46300005912781, "detail": "" } },
{ "pid": 1, "tid": 1, "ts": 6804717.28515625, "dur": 2455.00016212463, "ph": "X", "name": "Methods", "args": { "durationMS": 2.45500016212463, "detail": "Definitions" } },
{ "pid": 1, "tid": 1, "ts": 6811884.27734375, "dur": 5457.99970626831, "ph": "X", "name": "Convert", "args": { "durationMS": 5.45799970626831, "detail": "UnityEngine.VideoModule" } },
{ "pid": 1, "tid": 1, "ts": 6811886.23046875, "dur": 5454.99992370605, "ph": "X", "name": "Code", "args": { "durationMS": 5.45499992370605, "detail": "" } },
{ "pid": 1, "tid": 1, "ts": 6811896.97265625, "dur": 5443.99976730347, "ph": "X", "name": "Methods", "args": { "durationMS": 5.44399976730347, "detail": "Definitions" } },
{ "pid": 1, "tid": 1, "ts": 6821938.96484375, "dur": 442.999988794327, "ph": "X", "name": "Convert", "args": { "durationMS": 0.442999988794327, "detail": "UnityEngine" } },
{ "pid": 1, "tid": 1, "ts": 6821939.94140625, "dur": 442.00000166893, "ph": "X", "name": "Code", "args": { "durationMS": 0.44200000166893, "detail": "" } },
{ "pid": 1, "tid": 1, "ts": 6821946.77734375, "dur": 433.999985456467, "ph": "X", "name": "Methods", "args": { "durationMS": 0.433999985456467, "detail": "Definitions" } },
{ "pid": 1, "tid": 1, "ts": 6828076.66015625, "dur": 521.000027656555, "ph": "X", "name": "Convert", "args": { "durationMS": 0.521000027656555, "detail": "netstandard" } },
{ "pid": 1, "tid": 1, "ts": 6828079.1015625, "dur": 518.999993801117, "ph": "X", "name": "Code", "args": { "durationMS": 0.518999993801117, "detail": "" } },
{ "pid": 1, "tid": 1, "ts": 6828086.9140625, "dur": 510.999977588654, "ph": "X", "name": "Methods", "args": { "durationMS": 0.510999977588654, "detail": "Definitions" } },
{ "pid": 1, "tid": 1, "ts": 6833373.046875, "dur": 713505.065917969, "ph": "X", "name": "Convert", "args": { "durationMS": 713.505065917969, "detail": "UnityEngine.UI" } },
{ "pid": 1, "tid": 1, "ts": 6833375.48828125, "dur": 713502.014160156, "ph": "X", "name": "Code", "args": { "durationMS": 713.502014160156, "detail": "" } },
{ "pid": 1, "tid": 1, "ts": 6833447.265625, "dur": 713429.992675781, "ph": "X", "name": "Methods", "args": { "durationMS": 713.429992675781, "detail": "Definitions" } },
{ "pid": 1, "tid": 1, "ts": 7551114.2578125, "dur": 1054698.97460938, "ph": "X", "name": "Convert", "args": { "durationMS": 1054.69897460938, "detail": "Vuforia.UnityExtensions" } },
{ "pid": 1, "tid": 1, "ts": 7551114.74609375, "dur": 1054697.02148438, "ph": "X", "name": "Code", "args": { "durationMS": 1054.69702148438, "detail": "" } },
{ "pid": 1, "tid": 1, "ts": 7551233.88671875, "dur": 1054578.00292969, "ph": "X", "name": "Methods", "args": { "durationMS": 1054.57800292969, "detail": "Definitions" } },
{ "pid": 1, "tid": 1, "ts": 8612612.3046875, "dur": 25030.0006866455, "ph": "X", "name": "Convert", "args": { "durationMS": 25.0300006866455, "detail": "VuforiaScripts" } },
{ "pid": 1, "tid": 1, "ts": 8612615.234375, "dur": 25027.0004272461, "ph": "X", "name": "Code", "args": { "durationMS": 25.0270004272461, "detail": "" } },
{ "pid": 1, "tid": 1, "ts": 8612625, "dur": 25016.0007476807, "ph": "X", "name": "Methods", "args": { "durationMS": 25.0160007476807, "detail": "Definitions" } },
{ "pid": 1, "tid": 1, "ts": 8642540.0390625, "dur": 1398.00000190735, "ph": "X", "name": "Convert", "args": { "durationMS": 1.39800000190735, "detail": "Assembly-CSharp" } },
{ "pid": 1, "tid": 1, "ts": 8642541.015625, "dur": 1396.00002765656, "ph": "X", "name": "Code", "args": { "durationMS": 1.39600002765656, "detail": "" } },
{ "pid": 1, "tid": 1, "ts": 8642547.8515625, "dur": 1388.99993896484, "ph": "X", "name": "Methods", "args": { "durationMS": 1.38899993896484, "detail": "Definitions" } },
{ "pid": 1, "tid": 1, "ts": 8643943.359375, "dur": 3727066.16210938, "ph": "X", "name": "WriteGenerics", "args": { "durationMS": 3727.06616210938, "detail": "" } },
{ "pid": 1, "tid": 1, "ts": 8651656.25, "dur": 15064.9995803833, "ph": "X", "name": "Arrays Definitions", "args": { "durationMS": 15.0649995803833, "detail": "" } },
{ "pid": 1, "tid": 1, "ts": 8667212.890625, "dur": 782873.962402344, "ph": "X", "name": "GenericInstanceMethods", "args": { "durationMS": 782.873962402344, "detail": "" } },
{ "pid": 1, "tid": 1, "ts": 9450087.890625, "dur": 2546723.14453125, "ph": "X", "name": "GenericInstanceTypes", "args": { "durationMS": 2546.72314453125, "detail": "" } },
{ "pid": 1, "tid": 1, "ts": 11997217.7734375, "dur": 373781.005859375, "ph": "X", "name": "GenericComDefinitions", "args": { "durationMS": 373.781005859375, "detail": "" } },
{ "pid": 1, "tid": 1, "ts": 12384303.7109375, "dur": 311833.984375, "ph": "X", "name": "MetadataCollector", "args": { "durationMS": 311.833984375, "detail": "" } },
{ "pid": 1, "tid": 1, "ts": 12387092.7734375, "dur": 18516.0007476807, "ph": "X", "name": "UpdateEmptyTokens", "args": { "durationMS": 18.5160007476807, "detail": "" } },
{ "pid": 1, "tid": 1, "ts": 12407843.75, "dur": 16333.9996337891, "ph": "X", "name": "ValidateTokens", "args": { "durationMS": 16.3339996337891, "detail": "" } },
{ "pid": 1, "tid": 1, "ts": 12696425.78125, "dur": 2427.99997329712, "ph": "X", "name": "Write COM Callable Wrappers", "args": { "durationMS": 2.42799997329712, "detail": "" } },
{ "pid": 1, "tid": 1, "ts": 12698427.734375, "dur": 423.99999499321, "ph": "X", "name": "Collect implemented projected interfaces by COM Callable Wrappers", "args": { "durationMS": 0.42399999499321, "detail": "" } },
{ "pid": 1, "tid": 1, "ts": 12698853.515625, "dur": 2191852.05078125, "ph": "X", "name": "Metadata", "args": { "durationMS": 2191.85205078125, "detail": "Global" } },
{ "pid": 1, "tid": 1, "ts": 12774449.21875, "dur": 356015.014648438, "ph": "X", "name": "Attributes", "args": { "durationMS": 356.015014648438, "detail": "" } },
{ "pid": 1, "tid": 1, "ts": 13317924.8046875, "dur": 425897.979736328, "ph": "X", "name": "WriteCodeRegistration", "args": { "durationMS": 425.897979736328, "detail": "" } },
{ "pid": 1, "tid": 1, "ts": 13377476.5625, "dur": 10195.0006484985, "ph": "X", "name": "GenericContextCollector", "args": { "durationMS": 10.1950006484985, "detail": "Collect" } },
{ "pid": 1, "tid": 1, "ts": 13403279.296875, "dur": 361.999988555908, "ph": "X", "name": "GenericContextCollector", "args": { "durationMS": 0.361999988555908, "detail": "Collect" } },
{ "pid": 1, "tid": 1, "ts": 13417762.6953125, "dur": 602.999985218048, "ph": "X", "name": "GenericContextCollector", "args": { "durationMS": 0.602999985218048, "detail": "Collect" } },
{ "pid": 1, "tid": 1, "ts": 13481778.3203125, "dur": 3895.99990844727, "ph": "X", "name": "ReversePInvokerWrapperTable", "args": { "durationMS": 3.89599990844727, "detail": "Il2CppReversePInvokeWrapperTable.cpp" } },
{ "pid": 1, "tid": 1, "ts": 13486063.4765625, "dur": 119069.000244141, "ph": "X", "name": "GenericMethodPointerTable", "args": { "durationMS": 119.069000244141, "detail": "Il2CppGenericMethodPointerTable.cpp" } },
{ "pid": 1, "tid": 1, "ts": 13606263.671875, "dur": 121862.998962402, "ph": "X", "name": "InvokerTable", "args": { "durationMS": 121.862998962402, "detail": "Il2CppInvokerTable.cpp" } },
{ "pid": 1, "tid": 1, "ts": 13729437.5, "dur": 10088.99974823, "ph": "X", "name": "InteropDataTable", "args": { "durationMS": 10.08899974823, "detail": "Il2CppInteropDataTable.cpp" } },
{ "pid": 1, "tid": 1, "ts": 13743823.2421875, "dur": 1146881.10351562, "ph": "X", "name": "WriteMetadata", "args": { "durationMS": 1146.88110351562, "detail": "" } },
{ "pid": 1, "tid": 1, "ts": 13863642.578125, "dur": 4335.99996566772, "ph": "X", "name": "Metadata", "args": { "durationMS": 4.33599996566772, "detail": "Collect string literals" } },
{ "pid": 1, "tid": 1, "ts": 13969290.0390625, "dur": 92218.0023193359, "ph": "X", "name": "GenericClasses", "args": { "durationMS": 92.2180023193359, "detail": "" } },
{ "pid": 1, "tid": 1, "ts": 14061507.8125, "dur": 25208.9996337891, "ph": "X", "name": "GenericInst2", "args": { "durationMS": 25.2089996337891, "detail": "" } },
{ "pid": 1, "tid": 1, "ts": 14086717.7734375, "dur": 285601.013183594, "ph": "X", "name": "GenericMethods", "args": { "durationMS": 285.601013183594, "detail": "" } },
{ "pid": 1, "tid": 1, "ts": 14372319.3359375, "dur": 154556.991577148, "ph": "X", "name": "Il2CppTypes", "args": { "durationMS": 154.556991577148, "detail": "" } },
{ "pid": 1, "tid": 1, "ts": 14526875, "dur": 45395.0004577637, "ph": "X", "name": "GenericMethods", "args": { "durationMS": 45.3950004577637, "detail": "" } },
{ "pid": 1, "tid": 1, "ts": 14572271.484375, "dur": 138370.010375977, "ph": "X", "name": "CompilerCalculateTypeValues", "args": { "durationMS": 138.370010375977, "detail": "" } },
{ "pid": 1, "tid": 1, "ts": 14710642.578125, "dur": 3408.99991989136, "ph": "X", "name": "Registration", "args": { "durationMS": 3.40899991989136, "detail": "" } },
{ "pid": 1, "tid": 1, "ts": 14714268.5546875, "dur": 4914.00003433228, "ph": "X", "name": "StringLiteralWriter", "args": { "durationMS": 4.91400003433228, "detail": "" } },
{ "pid": 1, "tid": 1, "ts": 14719458.0078125, "dur": 945.999979972839, "ph": "X", "name": "Metadata Strings", "args": { "durationMS": 0.945999979972839, "detail": "" } },
{ "pid": 1, "tid": 1, "ts": 14720407.2265625, "dur": 2558.00008773804, "ph": "X", "name": "Events", "args": { "durationMS": 2.55800008773804, "detail": "" } },
{ "pid": 1, "tid": 1, "ts": 14722965.8203125, "dur": 4104.00009155273, "ph": "X", "name": "Properties", "args": { "durationMS": 4.10400009155273, "detail": "" } },
{ "pid": 1, "tid": 1, "ts": 14727070.3125, "dur": 60773.998260498, "ph": "X", "name": "Methods", "args": { "durationMS": 60.773998260498, "detail": "" } },
{ "pid": 1, "tid": 1, "ts": 14787845.703125, "dur": 897.000014781952, "ph": "X", "name": "Parameter Default Values", "args": { "durationMS": 0.897000014781952, "detail": "" } },
{ "pid": 1, "tid": 1, "ts": 14788744.140625, "dur": 1411.00001335144, "ph": "X", "name": "Field Default Values", "args": { "durationMS": 1.41100001335144, "detail": "" } },
{ "pid": 1, "tid": 1, "ts": 14790155.2734375, "dur": 437.000006437302, "ph": "X", "name": "Field and Parameter Default Values Data", "args": { "durationMS": 0.437000006437302, "detail": "" } },
{ "pid": 1, "tid": 1, "ts": 14790592.7734375, "dur": 671.000003814697, "ph": "X", "name": "Field Marshaled Sizes", "args": { "durationMS": 0.671000003814697, "detail": "" } },
{ "pid": 1, "tid": 1, "ts": 14791263.671875, "dur": 12510.9996795654, "ph": "X", "name": "Parameters", "args": { "durationMS": 12.5109996795654, "detail": "" } },
{ "pid": 1, "tid": 1, "ts": 14803774.4140625, "dur": 7103.00016403198, "ph": "X", "name": "Fields", "args": { "durationMS": 7.10300016403198, "detail": "" } },
{ "pid": 1, "tid": 1, "ts": 14810877.9296875, "dur": 1444.00000572205, "ph": "X", "name": "Generic Parameters", "args": { "durationMS": 1.44400000572205, "detail": "" } },
{ "pid": 1, "tid": 1, "ts": 14812323.2421875, "dur": 412.000000476837, "ph": "X", "name": "Generic Parameter Constraints", "args": { "durationMS": 0.412000000476837, "detail": "" } },
{ "pid": 1, "tid": 1, "ts": 14812735.3515625, "dur": 1568.99988651276, "ph": "X", "name": "Generic Containers", "args": { "durationMS": 1.56899988651276, "detail": "" } },
{ "pid": 1, "tid": 1, "ts": 14814304.6875, "dur": 418.000012636185, "ph": "X", "name": "Nested Types", "args": { "durationMS": 0.418000012636185, "detail": "" } },
{ "pid": 1, "tid": 1, "ts": 14814723.6328125, "dur": 416.999995708466, "ph": "X", "name": "Interfaces", "args": { "durationMS": 0.416999995708466, "detail": "" } },
{ "pid": 1, "tid": 1, "ts": 14815139.6484375, "dur": 1124.99988079071, "ph": "X", "name": "VTables", "args": { "durationMS": 1.12499988079071, "detail": "" } },
{ "pid": 1, "tid": 1, "ts": 14816265.625, "dur": 1372.99990653992, "ph": "X", "name": "Interface Offsets", "args": { "durationMS": 1.37299990653992, "detail": "" } },
{ "pid": 1, "tid": 1, "ts": 14817639.6484375, "dur": 47310.001373291, "ph": "X", "name": "Type Definitions", "args": { "durationMS": 47.310001373291, "detail": "" } },
{ "pid": 1, "tid": 1, "ts": 14864950.1953125, "dur": 6766.00027084351, "ph": "X", "name": "Images", "args": { "durationMS": 6.76600027084351, "detail": "" } },
{ "pid": 1, "tid": 1, "ts": 14871717.7734375, "dur": 5822.00002670288, "ph": "X", "name": "Assemblies", "args": { "durationMS": 5.82200002670288, "detail": "" } },
{ "pid": 1, "tid": 1, "ts": 14877541.015625, "dur": 1062.99996376038, "ph": "X", "name": "Metadata Usage Lists", "args": { "durationMS": 1.06299996376038, "detail": "" } },
{ "pid": 1, "tid": 1, "ts": 14878604.4921875, "dur": 1799.00002479553, "ph": "X", "name": "Metadata Usage Pairs", "args": { "durationMS": 1.79900002479553, "detail": "" } },
{ "pid": 1, "tid": 1, "ts": 14880654.296875, "dur": 421.000003814697, "ph": "X", "name": "Referenced Assemblies", "args": { "durationMS": 0.421000003814697, "detail": "" } },
{ "pid": 1, "tid": 1, "ts": 14881075.1953125, "dur": 2208.99987220764, "ph": "X", "name": "Attribute Types Ranges", "args": { "durationMS": 2.20899987220764, "detail": "" } },
{ "pid": 1, "tid": 1, "ts": 14883287.109375, "dur": 1455.9999704361, "ph": "X", "name": "Attribute Types", "args": { "durationMS": 1.4559999704361, "detail": "" } },
{ "pid": 1, "tid": 1, "ts": 14885073.2421875, "dur": 894.999980926514, "ph": "X", "name": "Unresolved Virtual Call Parameter Ranges", "args": { "durationMS": 0.894999980926514, "detail": "" } },
{ "pid": 1, "tid": 1, "ts": 14885968.75, "dur": 532.000005245209, "ph": "X", "name": "Windows Runtime type names", "args": { "durationMS": 0.532000005245209, "detail": "" } },
{ "pid": 1, "tid": 1, "ts": 14886501.953125, "dur": 1820.99997997284, "ph": "X", "name": "Exported Types", "args": { "durationMS": 1.82099997997284, "detail": "" } }
],
"meta_datetime": "06/12/2020 21:39:37",
"meta_command_line_args": "/Applications/Unity/Hub/Editor/2019.2.17f1/Unity.app/Contents/il2cpp/build/il2cppcore/il2cppcore.dll --convert-to-cpp --emit-null-checks --enable-array-bounds-check --dotnetprofile=unityaot --profiler-report --map-file-parser=/Applications/Unity/Hub/Editor/2019.2.17f1/Unity.app/Contents/Tools/MapFileParser/MapFileParser --directory=/Users/suvaneethan/Downloads/UnityGames/AR Card/Temp/StagingArea/Data/Managed --generatedcppdir=/Users/suvaneethan/Downloads/UnityGames/AR Card/Temp/il2cppOutput/il2cppOutput",
"meta_cpu_count": "4"}
